hydra_plugins/__init__.py
hydra_plugins/ray_launcher_badr/__init__.py
hydra_plugins/ray_launcher_badr/ray_launcher.py
hydra_plugins/ray_launcher_badr/conf/__init__.py
hydra_plugins/ray_launcher_badr/conf/hydra/launcher/ray.yaml
hydra_ray_launcher_badr-0.1.1.dist-info/METADATA
hydra_ray_launcher_badr-0.1.1.dist-info/WHEEL
hydra_ray_launcher_badr-0.1.1.dist-info/top_level.txt
hydra_ray_launcher_badr-0.1.1.dist-info/RECORD
