Metadata-Version: 2.1
Name: hydra-ray-launcher-badr
Version: 0.1.1
Summary: Hydra basic ray launcher
Home-page: https://github.com/BadrYoubiIdrissi/hydra-plugins
Author: Badr Youbi Idrissi
Author-email: badryoubiidrissi@gmail.com
License: UNKNOWN
Platform: UNKNOWN
Classifier: License :: OSI Approved :: MIT License
Classifier: Programming Language :: Python :: 2.7
Classifier: Programming Language :: Python :: 3.6
Classifier: Programming Language :: Python :: 3.7
Classifier: Operating System :: OS Independent
Requires-Dist: hydra-core
